{
  "status": "price_stale",
  "generated_at_jst": "2026-07-14T02:02:11.253476+09:00",
  "message": "価格未更新：日本株の価格日付が想定取引日 2026-07-13 より古いです。",
  "expected_price_date": "2026-07-13",
  "price_success_count": 25,
  "price_missing_count": 0,
  "jp_count": 25,
  "price_stale_count": 25,
  "price_stale_symbols": [
    "4063",
    "8601",
    "6383",
    "9861",
    "4368",
    "4901",
    "7821",
    "6287",
    "6902",
    "1911",
    "4042",
    "3405",
    "3402",
    "5020",
    "6326",
    "7267",
    "3407",
    "1928",
    "1377",
    "5401",
    "8410",
    "6501",
    "7974",
    "6758",
    "2871"
  ],
  "market_closed_count": 25,
  "warnings": [
    "価格未更新：日本株の価格日付が想定取引日 2026-07-13 より古いです。"
  ],
  "degradation_guard_attempt": true,
  "guarded_stem": "daily_jp",
  "stored_at_jst": "2026-07-14T02:02:11.253726+09:00"
}